devnarrate/__init__.py
devnarrate/git_operations.py
devnarrate/server.py
devnarrate-0.1.0a3.dist-info/METADATA
devnarrate-0.1.0a3.dist-info/WHEEL
devnarrate-0.1.0a3.dist-info/licenses/LICENSE
devnarrate-0.1.0a3.dist-info/RECORD
