Metadata-Version: 2.4
Name: devnarrate
Version: 0.1.0a3
Summary: MCP server that narrates your code changes, from commits to deployments.
Project-URL: Homepage, https://github.com/kmandana/DevNarrate
Project-URL: Documentation, https://pypi.org/project/devnarrate/
Author: K Man
Maintainer: K Man
License: MIT
License-File: LICENSE
Keywords: ai,claude,commit,git,mcp,pr
Classifier: Development Status :: 3 - Alpha
Classifier: Intended Audience :: Developers
Classifier: License :: OSI Approved :: MIT License
Classifier: Programming Language :: Python :: 3
Classifier: Programming Language :: Python :: 3.12
Classifier: Topic :: Software Development :: Libraries :: Python Modules
Classifier: Topic :: Software Development :: Version Control :: Git
Requires-Python: >=3.12
Requires-Dist: mcp[cli]>=1.20.0
Requires-Dist: tiktoken>=0.5.0
